ccalafiore/__init__.py
ccalafiore/array.py
ccalafiore/check.py
ccalafiore/clock.py
ccalafiore/combinations.py
ccalafiore/directory.py
ccalafiore/download.py
ccalafiore/format.py
ccalafiore/hacks.py
ccalafiore/image.py
ccalafiore/maths.py
ccalafiore/mixamo.py
ccalafiore/nn.py
ccalafiore/pkl.py
ccalafiore/shutdown.py
ccalafiore/strings.py
ccalafiore/txt.py
ccalafiore/plot/__init__.py
ccalafiore/plot/bars.py
ccalafiore/plot/cmaps.py
ccalafiore/plot/colors.py
ccalafiore/plot/heatmaps.py
ccalafiore/plot/parameters.py
ccalafiore/plot/points.py
ccalafiore/plot/save.py
ccalafiore/preprocessing/__init__.py
ccalafiore/preprocessing/axes_to_variables_table.py
ccalafiore/preprocessing/reorder_trials.py
ccalafiore/preprocessing/reshape.py
ccalafiore/preprocessing/rotate_indexes.py
ccalafiore/preprocessing/variables_table_to_axes/__init__.py
ccalafiore/preprocessing/variables_table_to_axes/balanced.py
ccalafiore/preprocessing/variables_table_to_axes/balanced_and_unbalanced.py
ccalafiore/preprocessing/variables_table_to_axes/balanced_or_unbalanced.py
ccalafiore/preprocessing/variables_table_to_axes/unbalanced.py
ccalafiore/stats/__init__.py
ccalafiore/stats/descriptive.py
ccalafiore/stats/exclusions.py
ccalafiore/stats/paired_t_test.py
ccalafiore/stats/unpaired_t_test.py
ccalafiore/stimulation/__init__.py
ccalafiore/stimulation/display.py
ccalafiore-0.0.60.dist-info/LICENSE.txt
ccalafiore-0.0.60.dist-info/METADATA
ccalafiore-0.0.60.dist-info/WHEEL
ccalafiore-0.0.60.dist-info/top_level.txt
ccalafiore-0.0.60.dist-info/RECORD
