Metadata-Version: 2.1
Name: ccalafiore
Version: 0.0.60
Summary: personal package
Home-page: https://pypi.org/project/ccalafiore/
Author: Carmelo Calafiore
Author-email: cc18849@essex.ac.uk
License: UNKNOWN
Platform: UNKNOWN
Classifier: Programming Language :: Python :: 3
Classifier: License :: OSI Approved :: MIT License
Classifier: Operating System :: OS Independent
Requires-Python: >=3.6
Requires-Dist: calapy
